OnyxCli/__init__.py
OnyxCli/CLASSES/__init__.py
OnyxCli/CLASSES/EnvConfElement.py
OnyxCli/CLASSES/NxComponant.py
OnyxCli/CLASSES/NxComponantAttributes.py
OnyxCli/CLASSES/NxOnyxApi.py
OnyxCli/CLASSES/NxProject.py
OnyxCli/CLASSES/NxTenant.py
OnyxCli/env.conf
OnyxCli/LIBS_BUS/__init__.py
OnyxCli/LIBS_BUS/apply_transco.py
OnyxCli/LIBS_BUS/compare_onyx_projects.py
OnyxCli/LIBS_BUS/find_onyx_project.py
OnyxCli/LIBS_BUS/load_env.py
OnyxCli/LIBS_BUS/read_onyx_project_api.py
OnyxCli/LIBS_BUS/read_onyx_project_package.py
OnyxCli/LIBS_BUS/write_to_disk_onyx_project.py
OnyxCli/LIBS_CLI/__init__.py
OnyxCli/LIBS_CLI/action_1.py
OnyxCli/LIBS_CLI/action_2.py
OnyxCli/LIBS_CLI/action_3.py
OnyxCli/LIBS_CLI/action_4.py
OnyxCli/LIBS_CLI/action_5.py
OnyxCli/LIBS_CLI/ask_package.py
OnyxCli/LIBS_CLI/ask_project.py
OnyxCli/LIBS_CLI/ask_tenant.py
OnyxCli/LIBS_CLI/check_project_existence.py
OnyxCli/LIBS_CLI/clear_screen.py
OnyxCli/LIBS_CLI/cli_add_to_workflow.py
OnyxCli/LIBS_CLI/cli_connect_api.py
OnyxCli/LIBS_CLI/cli_create_tenant.py
OnyxCli/LIBS_CLI/cli_get_connection.py
OnyxCli/LIBS_CLI/cli_get_id.py
OnyxCli/LIBS_CLI/cli_get_info.py
OnyxCli/LIBS_CLI/cli_get_organisation_unit.py
OnyxCli/LIBS_CLI/cli_tenant_validation.py
OnyxCli/LIBS_CLI/creer_arborescence.py
OnyxCli/LIBS_CLI/deploy_oConnections.py
OnyxCli/LIBS_CLI/deploy_oDataPipelines.py
OnyxCli/LIBS_CLI/deploy_oFileProviders.py
OnyxCli/LIBS_CLI/deploy_oForms.py
OnyxCli/LIBS_CLI/deploy_oNotifications.py
OnyxCli/LIBS_CLI/deploy_oPipelineColumns.py
OnyxCli/LIBS_CLI/deploy_oReports.py
OnyxCli/LIBS_CLI/deploy_oShellScripts.py
OnyxCli/LIBS_CLI/deploy_oSqlScripts.py
OnyxCli/LIBS_CLI/deploy_oVariables.py
OnyxCli/LIBS_CLI/deploy_oWidgetButton.py
OnyxCli/LIBS_CLI/deploy_oWidgetFilter.py
OnyxCli/LIBS_CLI/deploy_oWidgets.py
OnyxCli/LIBS_CLI/deploy_oWorkFlows.py
OnyxCli/LIBS_CLI/deploy_oWorkFlowStep.py
OnyxCli/LIBS_CLI/display_env.py
OnyxCli/LIBS_CLI/exist_envconf.py
OnyxCli/LIBS_CLI/exist_tenantName.py
OnyxCli/LIBS_CLI/get_connection_name.py
onyxcli-0.0.6.dist-info/METADATA
onyxcli-0.0.6.dist-info/WHEEL
onyxcli-0.0.6.dist-info/RECORD
