Metadata-Version: 2.1
Name: OnyxCli
Version: 0.0.6
Summary: CICD
License: MIT
Author: Olivier Siguré
Author-email: olivier.sigure@alchimiedatasolutions.com
Requires-Python: >=3.8,<4.0
Classifier: License :: OSI Approved :: MIT License
Classifier: Programming Language :: Python :: 3
Classifier: Programming Language :: Python :: 3.8
Classifier: Programming Language :: Python :: 3.9
Classifier: Programming Language :: Python :: 3.10
Classifier: Programming Language :: Python :: 3.11
Classifier: Programming Language :: Python :: 3.12
Requires-Dist: alive-progress (>=2.1.0,<3.0.0)
Requires-Dist: astor (>=0.8.1,<0.9.0)
Requires-Dist: click (>=8.0.4,<9.0.0)
Requires-Dist: pluggy (>=1.0.0,<2.0.0)
Requires-Dist: py (>=1.11.0,<2.0.0)
Requires-Dist: pyparsing (>=3.1.2,<4.0.0)
Requires-Dist: pytest (>=7.0.1,<8.0.0)
Requires-Dist: python-dotenv (>=0.20.0,<0.21.0)
Requires-Dist: requests (>=2.27.1,<3.0.0)
Requires-Dist: rich (>=12.6.0,<13.0.0)
Requires-Dist: tomli (>=1.2.3,<2.0.0)
Requires-Dist: urllib3 (>=1.26.18,<2.0.0)
Requires-Dist: zipp (>=3.6.0,<4.0.0)
